smt/__init__.py
smt/applications/__init__.py
smt/applications/application.py
smt/applications/cckrg.py
smt/applications/ego.py
smt/applications/mfck.py
smt/applications/mfk.py
smt/applications/mfkpls.py
smt/applications/mfkplsk.py
smt/applications/mixed_integer.py
smt/applications/moe.py
smt/applications/podi.py
smt/applications/smfck.py
smt/applications/smfk.py
smt/applications/vfm.py
smt/applications/tests/__init__.py
smt/applications/tests/test_cckrg.py
smt/applications/tests/test_ego.py
smt/applications/tests/test_mfck.py
smt/applications/tests/test_mfck_1fidelity.py
smt/applications/tests/test_mfk.py
smt/applications/tests/test_mfk_1fidelity.py
smt/applications/tests/test_mfk_mfkpls_mixed.py
smt/applications/tests/test_mfk_variance.py
smt/applications/tests/test_mfkpls.py
smt/applications/tests/test_mfkplsk.py
smt/applications/tests/test_mixed_integer.py
smt/applications/tests/test_moe.py
smt/applications/tests/test_podi.py
smt/applications/tests/test_save_load_moe_mfk.py
smt/applications/tests/test_smfck.py
smt/applications/tests/test_smfk.py
smt/applications/tests/test_vfm.py
smt/design_space/__init__.py
smt/design_space/design_space.py
smt/kernels/__init__.py
smt/kernels/kernels.py
smt/problems/__init__.py
smt/problems/branin.py
smt/problems/cantilever_beam.py
smt/problems/hierarchical_goldstein.py
smt/problems/lp_norm.py
smt/problems/mixed_cantilever_beam.py
smt/problems/ndim_cantilever_beam.py
smt/problems/ndim_robot_arm.py
smt/problems/ndim_rosenbrock.py
smt/problems/ndim_step_function.py
smt/problems/neural_network.py
smt/problems/problem.py
smt/problems/reduced_problem.py
smt/problems/robot_arm.py
smt/problems/rosenbrock.py
smt/problems/sphere.py
smt/problems/tensor_product.py
smt/problems/torsion_vibration.py
smt/problems/water_flow.py
smt/problems/water_flow_lfidelity.py
smt/problems/welded_beam.py
smt/problems/wing_weight.py
smt/sampling_methods/__init__.py
smt-2.10.1.dist-info/METADATA
smt-2.10.1.dist-info/WHEEL
smt-2.10.1.dist-info/top_level.txt
smt-2.10.1.dist-info/RECORD
smt-2.10.1.dist-info/licenses/LICENSE.txt
