Metadata-Version: 2.4
Name: smt
Version: 2.10.1
Summary: The Surrogate Modeling Toolbox (SMT)
Home-page: https://github.com/SMTorg/smt
Download-URL: https://github.com/SMTorg/smt/releases
Author: Remi Lafage et al.
Author-email: remi.lafage@onera.fr
License: BSD-3
Classifier: Development Status :: 5 - Production/Stable
Classifier: Intended Audience :: Science/Research
Classifier: Intended Audience :: Developers
Classifier: License :: OSI Approved :: BSD License
Classifier: Programming Language :: C++
Classifier: Programming Language :: Python
Classifier: Programming Language :: Python :: 3
Classifier: Programming Language :: Python :: 3.9
Classifier: Programming Language :: Python :: Implementation :: CPython
Classifier: Topic :: Software Development
Classifier: Topic :: Scientific/Engineering
Classifier: Operating System :: Microsoft :: Windows
Classifier: Operating System :: Unix
Classifier: Operating System :: MacOS
Requires-Python: >=3.9
License-File: LICENSE.txt
Requires-Dist: packaging
Requires-Dist: scikit-learn
Requires-Dist: pyDOE3>=1.5.0
Requires-Dist: scipy
Requires-Dist: jenn<3.0,>=2.0.0
Provides-Extra: numba
Requires-Dist: numba~=0.56.4; extra == "numba"
Provides-Extra: gpx
Requires-Dist: egobox~=0.32; extra == "gpx"
Dynamic: author
Dynamic: author-email
Dynamic: classifier
Dynamic: description
Dynamic: download-url
Dynamic: home-page
Dynamic: license
Dynamic: license-file
Dynamic: provides-extra
Dynamic: requires-dist
Dynamic: requires-python
Dynamic: summary
